{
  "name": "@aparajita/capacitor-dark-mode",
  "version": "3.3.3",
  "success": [
    "capacitor-android-4",
    "capacitor-ios-4"
  ],
  "repo": "https://github.com/aparajita/capacitor-dark-mode.git",
  "keywords": [
    "capacitor",
    "plugin",
    "native",
    "dark",
    "dark-mode"
  ],
  "fails": [
    "capacitor-ios-3",
    "capacitor-android-3",
    "cordova-ios-6",
    "cordova-android-11"
  ],
  "stars": 9,
  "image": "https://avatars.githubusercontent.com/u/22218?v=4",
  "description": "Universal dark mode support for Ionic web and native apps",
  "quality": 112,
  "updated": "2023-03-15T15:04:00Z",
  "versions": [
    "1.0.0",
    "1.0.1",
    "1.1.0",
    "2.0.0",
    "2.0.1",
    "2.0.2",
    "2.1.0",
    "3.0.0",
    "3.0.1",
    "3.0.2",
    "3.0.3",
    "3.1.0",
    "3.1.1",
    "3.2.0",
    "3.2.1",
    "3.3.0",
    "3.3.1",
    "3.3.2",
    "3.3.3"
  ],
  "author": "Aparajita Fishman",
  "bugs": "https://github.com/aparajita/capacitor-dark-mode/issues",
  "published": "2023-03-28T23:33:26.680Z",
  "downloads": 448
}