{
  "name": "@forgr/native-audio",
  "version": "3.1.1",
  "success": [
    "capacitor-ios-3"
  ],
  "repo": "https://github.com/riderx/native-audio.git",
  "author": "bazuka5801 <bazuka5801@mail.ru>",
  "published": "2022-04-15T14:08:34.639Z",
  "versions": [
    "3.0.2",
    "3.1.0",
    "3.1.1"
  ],
  "keywords": [
    "capacitor",
    "plugin",
    "audio",
    "media",
    "native"
  ],
  "fails": [
    "capacitor-android-3",
    "capacitor-ios-4",
    "capacitor-android-4"
  ],
  "description": "A native plugin for native audio engine",
  "bugs": "https://github.com/riderx/native-audio/issues",
  "quality": null
}