{
  "name": "@hmscore/cordova-plugin-hms-account",
  "version": "6.4.0-301",
  "success": [
    "capacitor-ios-3",
    "capacitor-ios-4",
    "cordova-android-11",
    "cordova-ios-6",
    "capacitor-ios-5"
  ],
  "keywords": [
    "cordova",
    "ecosystem:cordova",
    "cordova-android",
    "account",
    "huawei-account",
    "hms-account",
    "huawei",
    "hms"
  ],
  "fails": [
    "capacitor-android-3",
    "capacitor-android-4",
    "capacitor-android-5"
  ],
  "description": "Huawei Account Cordova Plugin",
  "bugs": "https://github.com/HMS-Core/hms-cordova-plugin/issues",
  "quality": null,
  "downloads": 53,
  "platforms": []
}