{
  "name": "cordova-plugin-admobpro",
  "version": "8.13.1",
  "success": [
    "cordova-ios-6"
  ],
  "repo": "https://github.com/floatinghotpot/cordova-admob-pro.git",
  "author": {
    "name": "Liming Xie"
  },
  "keywords": [
    "cordova",
    "admob",
    "plugin",
    "phonegap",
    "ionic",
    "capacitor",
    "nativescript",
    "appflow",
    "react-native",
    "reactnatvie",
    "meteor",
    "ad",
    "ecosystem:cordova",
    "cordova-android",
    "cordova-ios",
    "google",
    "ads",
    "eclipse",
    "android-studio",
    "simple",
    "easy",
    "android",
    "ios",
    "windows",
    "phonegap",
    "monetization",
    "monetisation",
    "money",
    "banner",
    "interstitial",
    "advertisement",
    "advertising",
    "earn",
    "cordova-admob",
    "admobpro",
    "iad",
    "flurry",
    "mobfox",
    "mopub",
    "inmobi",
    "chartboost",
    "domob",
    "rjfun",
    "admob-plugin",
    "cordova-plugin",
    "doubleclick",
    "google-admob"
  ],
  "fails": [
    "capacitor-android-4",
    "capacitor-ios-4",
    "capacitor-ios-3",
    "capacitor-android-3",
    "capacitor-android-5",
    "capacitor-ios-5",
    "cordova-android-11"
  ],
  "description": "Ultimate Cordova Plugin for Google AdMob and DFP to monetize hybrid apps. Show mobile Ad with single line of JavaScript. Compatible with Cordova CLI, Ionic, etc.",
  "bugs": "https://github.com/floatinghotpot/cordova-admob-pro/issues",
  "stars": 709,
  "image": "https://avatars.githubusercontent.com/u/2339512?v=4",
  "quality": 1219,
  "updated": "2023-04-11T18:56:55Z",
  "downloads": 351,
  "platforms": [
    "android",
    "ios"
  ],
  "fork": false,
  "published": "2022-06-13T23:44:33.736Z",
  "license": "MIT"
}