{
  "name": "cordova-plugin-otp-auto-verification",
  "version": "1.0.2",
  "success": [
    "capacitor-ios-4",
    "capacitor-ios-3",
    "cordova-ios-6",
    "capacitor-ios-5"
  ],
  "repo": "https://github.com/sandeepdillerao/cordova-plugin-otp-auto-verification.git",
  "author": {
    "name": "sandeep dillerao"
  },
  "keywords": [
    "ecosystem:cordova",
    "cordova-android"
  ],
  "fails": [
    "capacitor-android-4",
    "capacitor-android-3",
    "cordova-android-11",
    "capacitor-android-5"
  ],
  "description": "A plugin for Autoverification of OTP",
  "bugs": "https://github.com/sandeepdillerao/cordova-plugin-otp-auto-verification/issues",
  "stars": 12,
  "image": "https://avatars.githubusercontent.com/u/6266245?v=4",
  "quality": 138,
  "updated": "2021-12-15T06:38:16Z",
  "downloads": 172,
  "platforms": [
    "android"
  ],
  "fork": false
}