{
  "name": "cordova-plugin-fingerprint-aio",
  "version": "5.0.1",
  "success": [
    "capacitor-android-4",
    "capacitor-ios-4",
    "cordova-android-11",
    "capacitor-android-5",
    "capacitor-ios-5"
  ],
  "repo": "https://github.com/niklasmerz/cordova-plugin-fingerprint-aio.git",
  "author": {
    "name": "Niklas Merz"
  },
  "keywords": [
    "cordova",
    "plugin",
    "android",
    "fingerprint",
    "authentication",
    "ecosystem:cordova",
    "cordova-android",
    "cordova-ios",
    "ios",
    "biometric",
    "biometrics",
    "cordova-plugin",
    "cordova-plugin-fingerprint",
    "faceid",
    "fingerprint-authentication",
    "hacktoberfest",
    "ionic",
    "touchid"
  ],
  "fails": [
    "capacitor-ios-3",
    "capacitor-android-3",
    "cordova-ios-6"
  ],
  "description": "Cordova plugin to use fingerprint authentication on Android and iOS",
  "bugs": "https://github.com/niklasmerz/cordova-plugin-fingerprint-aio/issues",
  "stars": 295,
  "image": "https://avatars.githubusercontent.com/u/3585860?v=4",
  "quality": 620,
  "updated": "2023-04-01T12:58:34Z",
  "downloads": 31310,
  "platforms": [
    "android",
    "ios"
  ],
  "fork": false,
  "published": "2022-06-14T00:11:49.304Z",
  "license": "MIT"
}