{
  "name": "cordova-plugin-music-controls",
  "version": "2.2.0",
  "success": [
    "capacitor-android-4",
    "capacitor-ios-4",
    "capacitor-ios-3",
    "cordova-ios-6",
    "capacitor-android-5",
    "capacitor-ios-5"
  ],
  "repo": "https://github.com/homerours/cordova-music-controls-plugin.git",
  "author": {
    "name": "homerours"
  },
  "keywords": [
    "cordova",
    "music",
    "controller",
    "controls",
    "media",
    "plugin",
    "notification",
    "ecosystem:cordova",
    "cordova-android",
    "cordova-windows"
  ],
  "fails": [
    "capacitor-android-3",
    "cordova-android-11"
  ],
  "description": "Music controls for Cordova apps",
  "bugs": "https://github.com/homerours/cordova-music-controls-plugin/issues",
  "quality": 502,
  "downloads": 85,
  "stars": 152,
  "image": "https://avatars.githubusercontent.com/u/12702557?v=4",
  "updated": "2022-12-14T14:45:09Z",
  "platforms": [
    "android",
    "windows",
    "ios"
  ],
  "fork": false
}