{
  "name": "cordova-plugin-splashscreen",
  "version": "6.0.2",
  "success": [
    "capacitor-android-4",
    "capacitor-ios-4",
    "capacitor-ios-3",
    "cordova-android-11",
    "cordova-ios-6",
    "capacitor-android-5",
    "capacitor-ios-5"
  ],
  "repo": "https://github.com/apache/cordova-plugin-splashscreen.git",
  "author": {
    "name": "Apache Software Foundation"
  },
  "keywords": [
    "cordova",
    "splashscreen",
    "ecosystem:cordova",
    "cordova-android",
    "cordova-windows",
    "cordova-browser",
    "cplusplus",
    "csharp",
    "java",
    "javascript",
    "library",
    "mobile",
    "nodejs",
    "objective-c"
  ],
  "fails": [
    "capacitor-android-3"
  ],
  "description": "Cordova Splashscreen Plugin",
  "bugs": "https://github.com/apache/cordova-plugin-splashscreen/issues",
  "quality": 1396,
  "downloads": 156452,
  "stars": 637,
  "image": "https://avatars.githubusercontent.com/u/47359?v=4",
  "updated": "2023-03-27T17:00:48Z",
  "platforms": [
    "android",
    "windows",
    "browser"
  ],
  "fork": false
}