{
  "name": "cordova-plugin-cocoapod-support",
  "version": "1.6.2",
  "success": [
    "capacitor-android-4",
    "capacitor-ios-4",
    "cordova-android-11"
  ],
  "repo": "https://github.com/blakgeek/cordova-plugin-cocoapods-support.git",
  "published": "2022-12-11T19:33:56.680Z",
  "versions": [
    "1.0.1",
    "1.0.2",
    "1.0.3",
    "1.0.4",
    "1.0.6",
    "1.0.7",
    "1.1.0",
    "1.1.1",
    "1.2.0",
    "1.2.1",
    "1.2.2",
    "1.2.3",
    "1.2.5",
    "1.2.6",
    "1.2.7",
    "1.2.8",
    "1.2.9",
    "1.2.10",
    "1.2.11",
    "1.2.12",
    "1.2.13",
    "1.2.14",
    "1.2.16",
    "1.2.17",
    "1.2.18",
    "1.2.19",
    "1.2.20",
    "1.3.0",
    "1.5.0",
    "1.6.0",
    "1.6.2"
  ],
  "keywords": [
    "ecosystem:cordova",
    "cordova-ios",
    "cordova:plugin",
    "cocoapods",
    "pod",
    "pods",
    "plugin"
  ],
  "fails": [
    "capacitor-ios-3",
    "capacitor-android-3",
    "cordova-ios-6"
  ],
  "description": "A Cordova/PhoneGap plugin to add support for Cocoapod dependencies.",
  "bugs": "https://github.com/blakgeek/cordova-plugin-cocoapods-support/issues",
  "stars": 73,
  "image": "https://avatars.githubusercontent.com/u/824542?v=4",
  "quality": 252,
  "updated": "2023-01-28T09:37:14Z",
  "downloads": 4114
}